make_runner/__init__.py
make_runner/command_line.py
make_runner/makefile_parser.py
make_runner/run.py
make_runner/utils.py
make_runner-0.2.2.dist-info/entry_points.txt
make_runner-0.2.2.dist-info/LICENSE
make_runner-0.2.2.dist-info/WHEEL
make_runner-0.2.2.dist-info/METADATA
make_runner-0.2.2.dist-info/RECORD
