Metadata-Version: 2.1
Name: make-runner
Version: 0.2.2
Summary: Enhanced Makefile-based task runner
Home-page: https://github.com/de9uch1/make-runner
License: MIT
Author: Hiroyuki Deguchi
Author-email: deguchi.hiroyuki.db0@is.naist.jp
Requires-Python: >=3.7,<4.0
Classifier: License :: OSI Approved :: MIT License
Classifier: Programming Language :: Python :: 3
Classifier: Programming Language :: Python :: 3.10
Classifier: Programming Language :: Python :: 3.7
Classifier: Programming Language :: Python :: 3.8
Classifier: Programming Language :: Python :: 3.9
Project-URL: Repository, https://github.com/de9uch1/make-runner
